bzar/__init__.py
bzar/codec.py
bzar-1.0.2.dist-info/LICENSE
bzar-1.0.2.dist-info/METADATA
bzar-1.0.2.dist-info/WHEEL
bzar-1.0.2.dist-info/top_level.txt
bzar-1.0.2.dist-info/RECORD
