Metadata-Version: 2.1
Name: bzar
Version: 1.0.2
Summary: A python implementation for the bzar, a platform-independent format for numeric arrays
Home-page: https://github.com/gwappa/bzar-python
Author: Keisuke Sehara
Author-email: keisuke.sehara@gmail.com
License: MIT
Platform: UNKNOWN
Classifier: Development Status :: 3 - Alpha
Classifier: License :: OSI Approved :: MIT License
Classifier: Programming Language :: Python :: 3
